example.py
goat_sdk_example_langchain_uniswap-0.1.0.dist-info/METADATA
goat_sdk_example_langchain_uniswap-0.1.0.dist-info/WHEEL
goat_sdk_example_langchain_uniswap-0.1.0.dist-info/RECORD
